{"P11": {"labels": ["\u3010\u4e50\u4e50 \u7535\u8111\u79d1\u5b66\u3011\u7cbe\u54c1\u53d1\u5e03", "\u4e50\u4e50\u7535\u8111\u79d1\u5b66\u79d1\u6280\u7c7b"], "postTitle": "\u3010\u4e50\u4e50\u7535\u8111\u79d1\u5b66\u3011PyCharm\u548cPython\u5b89\u88c5\u6559\u7a0b", "postUrl": "post/%E3%80%90-le-le-dian-nao-ke-xue-%E3%80%91PyCharm-he-Python-an-zhuang-jiao-cheng.html", "createdDate": "2024-10-11", "dateLabelColor": "#bc4c00"}, "P10": {"labels": ["\u5b9e\u7528\u8f6f\u4ef6", "\u3010\u4e50\u4e50 \u7535\u8111\u79d1\u5b66\u3011\u7cbe\u54c1\u53d1\u5e03"], "postTitle": "\u3010\u4e50\u4e50\u7535\u8111\u79d1\u5b66\u3011\u8054\u60f3\u5e94\u7528\u5546\u5e97\u5b89\u88c5\u6559\u7a0b", "postUrl": "post/%E3%80%90-le-le-dian-nao-ke-xue-%E3%80%91-lian-xiang-ying-yong-shang-dian-an-zhuang-jiao-cheng.html", "createdDate": "2024-10-09", "dateLabelColor": "#bc4c00"}, "P9": {"labels": ["\u5b9e\u7528\u8f6f\u4ef6", "\u3010\u4e50\u4e50 \u7535\u8111\u79d1\u5b66\u3011\u7cbe\u54c1\u53d1\u5e03"], "postTitle": "\u3010\u7535\u8111\u79d1\u5b66\u3011Geek\u5220\u9664\u5de5\u5177", "postUrl": "post/%E3%80%90-dian-nao-ke-xue-%E3%80%91Geek-shan-chu-gong-ju.html", "createdDate": "2024-10-07", "dateLabelColor": "#bc4c00"}, "P8": {"labels": ["\u3010\u4e50\u4e50 \u7535\u8111\u79d1\u5b66\u3011\u7cbe\u54c1\u53d1\u5e03", "\u4e50\u4e50\u7535\u8111\u79d1\u5b66\u79d1\u6280\u7c7b"], "postTitle": "\u4e50\u4e50 \u7535\u8111\u79d1\u5b66-kali\u8bb2\u89e3/\u865a\u62df\u673a\u5b89\u88c5 \u6559\u7a0b", "postUrl": "post/le-le-%20-dian-nao-ke-xue--kali-jiang-jie---xu-ni-ji-an-zhuang-%20-jiao-cheng.html", "createdDate": "2024-09-28", "dateLabelColor": "#bc4c00"}, "P6": {"labels": ["documentation", "enhancement"], "postTitle": "liunx\u7cfb\u7edf\u865a\u62df\u673a\u5b89\u88c5\u6559\u7a0b", "postUrl": "post/liunx-xi-tong-xu-ni-ji-an-zhuang-jiao-cheng.html", "createdDate": "2024-09-21", "dateLabelColor": "#bc4c00"}, "P5": {"labels": ["documentation"], "postTitle": "VM\u865a\u62df\u673a\u5b89\u88c5\u6559\u7a0b", "postUrl": "post/VM-xu-ni-ji-an-zhuang-jiao-cheng.html", "createdDate": "2024-09-17", "dateLabelColor": "#bc4c00"}, "P4": {"labels": ["documentation"], "postTitle": "kali\u7cfb\u7edfU\u76d8\u5236\u4f5c\u6559\u7a0b", "postUrl": "post/kali-xi-tong-U-pan-zhi-zuo-jiao-cheng.html", "createdDate": "2024-09-16", "dateLabelColor": "#bc4c00"}, "P3": {"labels": ["documentation"], "postTitle": "kali linux\u7cfb\u7edf\u5b89\u88c5.\u8bb2\u89e3", "postUrl": "post/kali%20linux-xi-tong-an-zhuang-.-jiang-jie.html", "createdDate": "2024-09-07", "dateLabelColor": "#bc4c00"}, "P1": {"labels": ["documentation"], "postTitle": "\u4e50\u4e50lele\u7535\u8111\u79d1\u5b66\u7f51", "postUrl": "post/le-le-lele-dian-nao-ke-xue-wang.html", "createdDate": "2024-09-07", "dateLabelColor": "#bc4c00"}, "labelColorDict": {"\u3010\u4e50\u4e50 \u7535\u8111\u79d1\u5b66\u3011\u7cbe\u54c1\u53d1\u5e03": "#7CF36C", "bug": "#d73a4a", "documentation": "#0075ca", "duplicate": "#cfd3d7", "enhancement": "#a2eeef", "good first issue": "#7057ff", "help wanted": "#008672", "invalid": "#e4e669", "question": "#d876e3", "wontfix": "#ffffff", "\u4e50\u4e50\u7535\u8111\u79d1\u5b66\u72ec\u5bb6\u51fa\u54c1": "#C23038", "\u4e50\u4e50\u7535\u8111\u79d1\u5b66\u79d1\u6280\u7c7b": "#b60205", "\u5b9e\u7528\u8f6f\u4ef6": "#5430C7"}}